{"devicePlatform":"","logFolder":"C:\\Users\\cipta.andhika\\Katalon Studio\\Blanja_Mobile_Pulsa\\Reports\\AutoplacedMweb_Reguler\\TS_11_Autoplaced_BRI_BankTransfer\\20181016_160527","runData":{"hostName":"cipta.andhika - CIPTA-E460.ad.metraplasa.co.id","os":"Windows 10 64bit","katalonVersion":"5.8.0.1","browser":"Chrome 65.0.3302.0","hostAddress":"10.10.99.244","sessionId":"0d8868f35c54d3b68038c3d793d81819","seleniumVersion":"3.7.1","proxyInformation":"ProxyInformation{proxyOption\u003dNO_PROXY, proxyServerType\u003dHTTP, password\u003d, proxyServerAddress\u003d, proxyServerPort\u003d0}","platform":"Windows 10"},"type":"TEST_SUITE","name":"TS_11_Autoplaced_BRI_BankTransfer","id":"Test Suites/AutoplacedMweb_Reguler/TS_11_Autoplaced_BRI_BankTransfer","source":"","message":"Test Cases/03_Trade/ChooseMethodPaymentMobileReguler/TC_ClickCheckout_GetLastOrderID_ExportTo_Blanja_Autoplaced","description":"","startTime":1539681066671,"endTime":1539681100031,"childRecords":[{"isOptional":false,"type":"TEST_CASE","name":"Test Cases/01_Member/Login_Reguler","id":"Test Cases/01_Member/Login_Reguler","source":"C:\\\\Users\\\\cipta.andhika\\\\Katalon Studio\\\\Blanja_Mobile_Pulsa\\\\Test Cases\\\\01_Member\\\\Login_Reguler.tc","message":"Test Cases/01_Member/Login_Reguler","description":"","startTime":1539681067034,"endTime":1539681075780,"childRecords":[{"testStatus":{"stackTrace":"","statusValue":"INFO"},"type":"MESSAGE","name":"","message":"Evaluating variables for test case","startTime":1539681067056,"endTime":0,"childRecords":[],"interuppted":false},{"index":1,"isIgnoredIfFailed":false,"type":"TEST_STEP","name":"openBrowser","message":"Browser is opened with url: \u0027\u0027","description":"","startTime":1539681067362,"endTime":1539681070602,"childRecords":[{"testStatus":{"stackTrace":"","statusValue":"PASSED"},"type":"MESSAGE","name":"","message":"Browser is opened with url: \u0027\u0027","startTime":1539681070601,"endTime":0,"childRecords":[],"interuppted":false}],"interuppted":false},{"index":2,"isIgnoredIfFailed":false,"type":"TEST_STEP","name":"navigateToUrl","message":"Navigate to \u0027https://m.blanja.com/member/login\u0027 successfully","description":"","startTime":1539681070602,"endTime":1539681072431,"childRecords":[{"testStatus":{"stackTrace":"","statusValue":"PASSED"},"type":"MESSAGE","name":"","message":"Navigate to \u0027https://m.blanja.com/member/login\u0027 successfully","startTime":1539681072430,"endTime":0,"childRecords":[],"interuppted":false}],"interuppted":false},{"index":3,"isIgnoredIfFailed":false,"type":"TEST_STEP","name":"setText","message":"Text \u0027testblj2\u0027 is set on object \u0027Object Repository/Member_Login/username\u0027","description":"","startTime":1539681072431,"endTime":1539681072662,"childRecords":[{"testStatus":{"stackTrace":"","statusValue":"PASSED"},"type":"MESSAGE","name":"","message":"Text \u0027testblj2\u0027 is set on object \u0027Object Repository/Member_Login/username\u0027","startTime":1539681072661,"endTime":0,"childRecords":[],"interuppted":false}],"interuppted":false},{"index":4,"isIgnoredIfFailed":false,"type":"TEST_STEP","name":"setText","message":"Text \u0027123qwe\u0027 is set on object \u0027Object Repository/Member_Login/password\u0027","description":"","startTime":1539681072662,"endTime":1539681072804,"childRecords":[{"testStatus":{"stackTrace":"","statusValue":"PASSED"},"type":"MESSAGE","name":"","message":"Text \u0027123qwe\u0027 is set on object \u0027Object Repository/Member_Login/password\u0027","startTime":1539681072804,"endTime":0,"childRecords":[],"interuppted":false}],"interuppted":false},{"index":5,"isIgnoredIfFailed":false,"type":"TEST_STEP","name":"click","message":"Object: \u0027Object Repository/Member_Login/Button_Masuk\u0027 is clicked on","description":"","startTime":1539681072805,"endTime":1539681073756,"childRecords":[{"testStatus":{"stackTrace":"","statusValue":"PASSED"},"type":"MESSAGE","name":"","message":"Object: \u0027Object Repository/Member_Login/Button_Masuk\u0027 is clicked on","startTime":1539681073755,"endTime":0,"childRecords":[],"interuppted":false}],"interuppted":false},{"index":6,"isIgnoredIfFailed":false,"type":"TEST_STEP","name":"delay","message":"Delayed 2 second(s)","description":"","startTime":1539681073756,"endTime":1539681075779,"childRecords":[{"testStatus":{"stackTrace":"","statusValue":"PASSED"},"type":"MESSAGE","name":"","message":"Delayed 2 second(s)","startTime":1539681075778,"endTime":0,"childRecords":[],"interuppted":false}],"interuppted":false},{"testStatus":{"stackTrace":"","statusValue":"PASSED"},"type":"MESSAGE","name":"","message":"Test Cases/01_Member/Login_Reguler","startTime":1539681075779,"endTime":0,"childRecords":[],"interuppted":false}],"interuppted":false},{"isOptional":false,"type":"TEST_CASE","name":"Test Cases/02_PDP/PDP_Reguler","id":"Test Cases/02_PDP/PDP_Reguler","source":"C:\\\\Users\\\\cipta.andhika\\\\Katalon Studio\\\\Blanja_Mobile_Pulsa\\\\Test Cases\\\\02_PDP\\\\PDP_Reguler.tc","message":"Test Cases/02_PDP/PDP_Reguler","description":"","startTime":1539681075782,"endTime":1539681093585,"childRecords":[{"testStatus":{"stackTrace":"","statusValue":"INFO"},"type":"MESSAGE","name":"","message":"Evaluating variables for test case","startTime":1539681075793,"endTime":0,"childRecords":[],"interuppted":false},{"index":1,"isIgnoredIfFailed":false,"type":"TEST_STEP","name":"navigateToUrl","message":"Navigate to \u0027https://m.blanja.com/item/jual-beli-pantene-black-shine-18983897\u0027 successfully","description":"","startTime":1539681075996,"endTime":1539681080550,"childRecords":[{"testStatus":{"stackTrace":"","statusValue":"PASSED"},"type":"MESSAGE","name":"","message":"Navigate to \u0027https://m.blanja.com/item/jual-beli-pantene-black-shine-18983897\u0027 successfully","startTime":1539681080549,"endTime":0,"childRecords":[],"interuppted":false}],"interuppted":false},{"index":2,"isIgnoredIfFailed":false,"type":"TEST_STEP","name":"delay","message":"Delayed 2 second(s)","description":"","startTime":1539681080551,"endTime":1539681082557,"childRecords":[{"testStatus":{"stackTrace":"","statusValue":"PASSED"},"type":"MESSAGE","name":"","message":"Delayed 2 second(s)","startTime":1539681082555,"endTime":0,"childRecords":[],"interuppted":false}],"interuppted":false},{"index":3,"isIgnoredIfFailed":false,"type":"TEST_STEP","name":"click","message":"Object: \u0027Object Repository/PDP/close_dialog_gojek\u0027 is clicked on","description":"","startTime":1539681082558,"endTime":1539681082680,"childRecords":[{"testStatus":{"stackTrace":"","statusValue":"PASSED"},"type":"MESSAGE","name":"","message":"Object: \u0027Object Repository/PDP/close_dialog_gojek\u0027 is clicked on","startTime":1539681082679,"endTime":0,"childRecords":[],"interuppted":false}],"interuppted":false},{"index":4,"isIgnoredIfFailed":false,"type":"TEST_STEP","name":"delay","message":"Delayed 2 second(s)","description":"","startTime":1539681082681,"endTime":1539681084683,"childRecords":[{"testStatus":{"stackTrace":"","statusValue":"PASSED"},"type":"MESSAGE","name":"","message":"Delayed 2 second(s)","startTime":1539681084682,"endTime":0,"childRecords":[],"interuppted":false}],"interuppted":false},{"index":5,"isIgnoredIfFailed":false,"type":"TEST_STEP","name":"click","message":"Object: \u0027Object Repository/PDP/Btn_tambah_ketroli\u0027 is clicked on","description":"","startTime":1539681084683,"endTime":1539681084789,"childRecords":[{"testStatus":{"stackTrace":"","statusValue":"PASSED"},"type":"MESSAGE","name":"","message":"Object: \u0027Object Repository/PDP/Btn_tambah_ketroli\u0027 is clicked on","startTime":1539681084788,"endTime":0,"childRecords":[],"interuppted":false}],"interuppted":false},{"index":6,"isIgnoredIfFailed":false,"type":"TEST_STEP","name":"delay","message":"Delayed 2 second(s)","description":"","startTime":1539681084789,"endTime":1539681086792,"childRecords":[{"testStatus":{"stackTrace":"","statusValue":"PASSED"},"type":"MESSAGE","name":"","message":"Delayed 2 second(s)","startTime":1539681086790,"endTime":0,"childRecords":[],"interuppted":false}],"interuppted":false},{"index":7,"isIgnoredIfFailed":false,"type":"TEST_STEP","name":"click","message":"Object: \u0027Object Repository/PDP/Btn_ke_pembayaran\u0027 is clicked on","description":"","startTime":1539681086793,"endTime":1539681087940,"childRecords":[{"testStatus":{"stackTrace":"","statusValue":"PASSED"},"type":"MESSAGE","name":"","message":"Object: \u0027Object Repository/PDP/Btn_ke_pembayaran\u0027 is clicked on","startTime":1539681087938,"endTime":0,"childRecords":[],"interuppted":false}],"interuppted":false},{"index":8,"isIgnoredIfFailed":false,"type":"TEST_STEP","name":"delay","message":"Delayed 2 second(s)","description":"","startTime":1539681087940,"endTime":1539681089944,"childRecords":[{"testStatus":{"stackTrace":"","statusValue":"PASSED"},"type":"MESSAGE","name":"","message":"Delayed 2 second(s)","startTime":1539681089942,"endTime":0,"childRecords":[],"interuppted":false}],"interuppted":false},{"index":9,"isIgnoredIfFailed":false,"type":"TEST_STEP","name":"click","message":"Object: \u0027Object Repository/PDP/Btn_Pembayaran\u0027 is clicked on","description":"","startTime":1539681089946,"endTime":1539681093583,"childRecords":[{"testStatus":{"stackTrace":"","statusValue":"PASSED"},"type":"MESSAGE","name":"","message":"Object: \u0027Object Repository/PDP/Btn_Pembayaran\u0027 is clicked on","startTime":1539681093582,"endTime":0,"childRecords":[],"interuppted":false}],"interuppted":false},{"testStatus":{"stackTrace":"","statusValue":"PASSED"},"type":"MESSAGE","name":"","message":"Test Cases/02_PDP/PDP_Reguler","startTime":1539681093584,"endTime":0,"childRecords":[],"interuppted":false}],"interuppted":false},{"isOptional":false,"type":"TEST_CASE","name":"Test Cases/03_Trade/ChooseMethodPaymentMobileReguler/TC_11_ChooseMethodPayment_BRI_BankTransfer","id":"Test Cases/03_Trade/ChooseMethodPaymentMobileReguler/TC_11_ChooseMethodPayment_BRI_BankTransfer","source":"C:\\\\Users\\\\cipta.andhika\\\\Katalon Studio\\\\Blanja_Mobile_Pulsa\\\\Test Cases\\\\03_Trade\\\\ChooseMethodPaymentMobileReguler\\\\TC_11_ChooseMethodPayment_BRI_BankTransfer.tc","message":"Test Cases/03_Trade/ChooseMethodPaymentMobileReguler/TC_11_ChooseMethodPayment_BRI_BankTransfer","description":"","startTime":1539681093590,"endTime":1539681096265,"childRecords":[{"testStatus":{"stackTrace":"","statusValue":"INFO"},"type":"MESSAGE","name":"","message":"Evaluating variables for test case","startTime":1539681093599,"endTime":0,"childRecords":[],"interuppted":false},{"index":1,"isIgnoredIfFailed":false,"type":"TEST_STEP","name":"selectOptionByLabel","message":"All options with label \u0027Kurir Standar\u0027 are selected in object \u0027Object Repository/Jasa_Pengiriman/Pilih_Pengiriman\u0027 ","description":"","startTime":1539681093737,"endTime":1539681093886,"childRecords":[{"testStatus":{"stackTrace":"","statusValue":"PASSED"},"type":"MESSAGE","name":"","message":"All options with label \u0027Kurir Standar\u0027 are selected in object \u0027Object Repository/Jasa_Pengiriman/Pilih_Pengiriman\u0027 ","startTime":1539681093885,"endTime":0,"childRecords":[],"interuppted":false}],"interuppted":false},{"index":2,"isIgnoredIfFailed":false,"type":"TEST_STEP","name":"delay","message":"Delayed 1 second(s)","description":"","startTime":1539681093886,"endTime":1539681094888,"childRecords":[{"testStatus":{"stackTrace":"","statusValue":"PASSED"},"type":"MESSAGE","name":"","message":"Delayed 1 second(s)","startTime":1539681094887,"endTime":0,"childRecords":[],"interuppted":false}],"interuppted":false},{"index":3,"isIgnoredIfFailed":false,"type":"TEST_STEP","name":"click","message":"Object: \u0027Object Repository/Trade_Payment_Method/Click_Bank/ClickBank/Click_03_BRI\u0027 is clicked on","description":"","startTime":1539681094889,"endTime":1539681095068,"childRecords":[{"testStatus":{"stackTrace":"","statusValue":"PASSED"},"type":"MESSAGE","name":"","message":"Object: \u0027Object Repository/Trade_Payment_Method/Click_Bank/ClickBank/Click_03_BRI\u0027 is clicked on","startTime":1539681095067,"endTime":0,"childRecords":[],"interuppted":false}],"interuppted":false},{"index":4,"isIgnoredIfFailed":false,"type":"TEST_STEP","name":"delay","message":"Delayed 1 second(s)","description":"","startTime":1539681095068,"endTime":1539681096071,"childRecords":[{"testStatus":{"stackTrace":"","statusValue":"PASSED"},"type":"MESSAGE","name":"","message":"Delayed 1 second(s)","startTime":1539681096070,"endTime":0,"childRecords":[],"interuppted":false}],"interuppted":false},{"index":5,"isIgnoredIfFailed":false,"type":"TEST_STEP","name":"click","message":"Object: \u0027Object Repository/Trade_Payment_Method/Click_Bank/BRI_Reguler/Click_10_BRI_BankTransfer\u0027 is clicked on","description":"","startTime":1539681096072,"endTime":1539681096239,"childRecords":[{"testStatus":{"stackTrace":"","statusValue":"PASSED"},"type":"MESSAGE","name":"","message":"Object: \u0027Object Repository/Trade_Payment_Method/Click_Bank/BRI_Reguler/Click_10_BRI_BankTransfer\u0027 is clicked on","startTime":1539681096238,"endTime":0,"childRecords":[],"interuppted":false}],"interuppted":false},{"index":6,"isIgnoredIfFailed":false,"type":"TEST_STEP","name":"blj.common.report.Autoplaced.AppendToBlanjaAutoplacedReport","message":"blj.common.report.Autoplaced.AppendToBlanjaAutoplacedReport is PASSED","description":"","startTime":1539681096239,"endTime":1539681096264,"childRecords":[{"testStatus":{"stackTrace":"","statusValue":"PASSED"},"type":"MESSAGE","name":"","message":"blj.common.report.Autoplaced.AppendToBlanjaAutoplacedReport is PASSED","startTime":1539681096264,"endTime":0,"childRecords":[],"interuppted":false}],"interuppted":false},{"testStatus":{"stackTrace":"","statusValue":"PASSED"},"type":"MESSAGE","name":"","message":"Test Cases/03_Trade/ChooseMethodPaymentMobileReguler/TC_11_ChooseMethodPayment_BRI_BankTransfer","startTime":1539681096264,"endTime":0,"childRecords":[],"interuppted":false}],"interuppted":false},{"isOptional":false,"type":"TEST_CASE","name":"Test Cases/03_Trade/ChooseMethodPaymentMobileReguler/TC_ClickCheckout_GetLastOrderID_ExportTo_Blanja_Autoplaced","id":"Test Cases/03_Trade/ChooseMethodPaymentMobileReguler/TC_ClickCheckout_GetLastOrderID_ExportTo_Blanja_Autoplaced","source":"C:\\\\Users\\\\cipta.andhika\\\\Katalon Studio\\\\Blanja_Mobile_Pulsa\\\\Test Cases\\\\03_Trade\\\\ChooseMethodPaymentMobileReguler\\\\TC_ClickCheckout_GetLastOrderID_ExportTo_Blanja_Autoplaced.tc","message":"Test Cases/03_Trade/ChooseMethodPaymentMobileReguler/TC_ClickCheckout_GetLastOrderID_ExportTo_Blanja_Autoplaced","description":"","startTime":1539681096268,"endTime":1539681099284,"childRecords":[{"testStatus":{"stackTrace":"","statusValue":"INFO"},"type":"MESSAGE","name":"","message":"Evaluating variables for test case","startTime":1539681096281,"endTime":0,"childRecords":[],"interuppted":false},{"testStatus":{"stackTrace":"","statusValue":"INFO"},"type":"MESSAGE","name":"","message":"Variable \u0027memberOrderListUrl\u0027 is set to https://m.blanja.com/mobile/trades/index as default","startTime":1539681096330,"endTime":0,"childRecords":[],"interuppted":false},{"index":1,"isIgnoredIfFailed":false,"type":"TEST_STEP","name":"delay","message":"Delayed 1 second(s)","description":"","startTime":1539681096444,"endTime":1539681097449,"childRecords":[{"testStatus":{"stackTrace":"","statusValue":"PASSED"},"type":"MESSAGE","name":"","message":"Delayed 1 second(s)","startTime":1539681097447,"endTime":0,"childRecords":[],"interuppted":false}],"interuppted":false},{"index":2,"isIgnoredIfFailed":false,"type":"TEST_STEP","name":"click","message":"Object: \u0027Object Repository/Trade_Payment_Method/input_checkOut_Reguler\u0027 is clicked on","description":"","startTime":1539681097450,"endTime":1539681097567,"childRecords":[{"testStatus":{"stackTrace":"","statusValue":"PASSED"},"type":"MESSAGE","name":"","message":"Object: \u0027Object Repository/Trade_Payment_Method/input_checkOut_Reguler\u0027 is clicked on","startTime":1539681097566,"endTime":0,"childRecords":[],"interuppted":false}],"interuppted":false},{"index":3,"isIgnoredIfFailed":false,"type":"TEST_STEP","name":"navigateToUrl","message":"Navigate to \u0027https://m.blanja.com/mobile/trades/index\u0027 successfully","description":"","startTime":1539681097567,"endTime":1539681098135,"childRecords":[{"testStatus":{"stackTrace":"","statusValue":"PASSED"},"type":"MESSAGE","name":"","message":"Navigate to \u0027https://m.blanja.com/mobile/trades/index\u0027 successfully","startTime":1539681098134,"endTime":0,"childRecords":[],"interuppted":false}],"interuppted":false},{"index":4,"isIgnoredIfFailed":false,"type":"TEST_STEP","name":"Statement - orderNumber \u003d \" - \" + com.kms.katalon.core.webui.keyword.WebUiBuiltInKeywords.getText(com.kms.katalon.core.testobject.ObjectRepository.findTestObject(Member_BlanjaanSaya/Label_FirstOrderNumber))","message":"Text of object \u0027Object Repository/Member_BlanjaanSaya/Label_FirstOrderNumber\u0027 is: \u0027No. Order : 418692810304484019\n16 Okt 2018 16:10\nPantene Black Shine\n  Rp 20.000 x 1\u0027","description":"","startTime":1539681098135,"endTime":1539681099259,"childRecords":[{"testStatus":{"stackTrace":"","statusValue":"PASSED"},"type":"MESSAGE","name":"","message":"Text of object \u0027Object Repository/Member_BlanjaanSaya/Label_FirstOrderNumber\u0027 is: \u0027No. Order : 418692810304484019\n16 Okt 2018 16:10\nPantene Black Shine\n  Rp 20.000 x 1\u0027","startTime":1539681099258,"endTime":0,"childRecords":[],"interuppted":false}],"interuppted":false},{"index":5,"isIgnoredIfFailed":false,"type":"TEST_STEP","name":"blj.common.report.Autoplaced.AppendToBlanjaAutoplacedReport","message":"blj.common.report.Autoplaced.AppendToBlanjaAutoplacedReport is PASSED","description":"","startTime":1539681099259,"endTime":1539681099273,"childRecords":[{"testStatus":{"stackTrace":"","statusValue":"PASSED"},"type":"MESSAGE","name":"","message":"blj.common.report.Autoplaced.AppendToBlanjaAutoplacedReport is PASSED","startTime":1539681099273,"endTime":0,"childRecords":[],"interuppted":false}],"interuppted":false},{"index":6,"isIgnoredIfFailed":false,"type":"TEST_STEP","name":"blj.common.report.Autoplaced.AppendToBlanjaAutoplacedReport","message":"blj.common.report.Autoplaced.AppendToBlanjaAutoplacedReport is PASSED","description":"","startTime":1539681099273,"endTime":1539681099282,"childRecords":[{"testStatus":{"stackTrace":"","statusValue":"PASSED"},"type":"MESSAGE","name":"","message":"blj.common.report.Autoplaced.AppendToBlanjaAutoplacedReport is PASSED","startTime":1539681099281,"endTime":0,"childRecords":[],"interuppted":false}],"interuppted":false},{"testStatus":{"stackTrace":"","statusValue":"PASSED"},"type":"MESSAGE","name":"","message":"Test Cases/03_Trade/ChooseMethodPaymentMobileReguler/TC_ClickCheckout_GetLastOrderID_ExportTo_Blanja_Autoplaced","startTime":1539681099283,"endTime":0,"childRecords":[],"interuppted":false}],"interuppted":false}],"interuppted":false}